quittance/__init__.py
quittance/__main__.py
quittance/templates/pacifico.ttf
quittance/templates/quittance.css
quittance/templates/quittance.html
quittance/templates/sourcesanspro-bold.otf
quittance/templates/sourcesanspro-regular.otf
quittance-0.1.dist-info/METADATA
quittance-0.1.dist-info/WHEEL
quittance-0.1.dist-info/entry_points.txt
quittance-0.1.dist-info/top_level.txt
quittance-0.1.dist-info/RECORD
