Metadata-Version: 2.1
Name: quittance
Version: 0.1
Summary: Génère des quittances de loyers.
Author-email: Julien Palard <julien@palard.fr>
License: MIT License
Project-URL: homepage, https://git.afpy.org/mdk/quittance
Requires-Python: >=3.7
Requires-Dist: weasyprint
Requires-Dist: tomlkit
Requires-Dist: jinja2
